swagger_client/__init__.py
swagger_client/api_client.py
swagger_client/configuration.py
swagger_client/rest.py
swagger_client/api/__init__.py
swagger_client/api/autocomplete_api.py
swagger_client/api/deleted_entities_api.py
swagger_client/api/entity_api.py
swagger_client/api/search_api.py
swagger_client/models/__init__.py
swagger_client/models/acquisition.py
swagger_client/models/acquisition_entity.py
swagger_client/models/acquisition_entity_cards.py
swagger_client/models/acquisition_search_results.py
swagger_client/models/address.py
swagger_client/models/address_entity.py
swagger_client/models/address_entity_cards.py
swagger_client/models/address_search_results.py
swagger_client/models/all_of_acquisition_acquiree_funding_total.py
swagger_client/models/all_of_acquisition_acquiree_identifier.py
swagger_client/models/all_of_acquisition_acquirer_funding_total.py
swagger_client/models/all_of_acquisition_acquirer_identifier.py
swagger_client/models/all_of_acquisition_announced_on.py
swagger_client/models/all_of_acquisition_completed_on.py
swagger_client/models/all_of_acquisition_identifier.py
swagger_client/models/all_of_acquisition_price.py
swagger_client/models/all_of_address_headquartered_organization_identifier.py
swagger_client/models/all_of_address_identifier.py
swagger_client/models/all_of_category_group_identifier.py
swagger_client/models/all_of_category_identifier.py
swagger_client/models/all_of_degree_completed_on.py
swagger_client/models/all_of_degree_identifier.py
swagger_client/models/all_of_degree_person_identifier.py
swagger_client/models/all_of_degree_school_identifier.py
swagger_client/models/all_of_degree_started_on.py
swagger_client/models/all_of_event_appearance_event_identifier.py
swagger_client/models/all_of_event_appearance_identifier.py
swagger_client/models/all_of_event_appearance_participant_identifier.py
swagger_client/models/all_of_event_event_url.py
swagger_client/models/all_of_event_identifier.py
python_crunchbase_client-1.0.0.dist-info/LICENSE
python_crunchbase_client-1.0.0.dist-info/METADATA
python_crunchbase_client-1.0.0.dist-info/WHEEL
python_crunchbase_client-1.0.0.dist-info/top_level.txt
python_crunchbase_client-1.0.0.dist-info/RECORD
